{"ongoing_trials": {"tuner0": "237cd0baa5bb1485ff560e1d5aa7ab33"}, "hyperparameters": {"space": [{"class_name": "Choice", "config": {"name": "activation", "default": "relu", "conditions": [], "values": ["relu", "tanh", "sigmoid"], "ordered": false}}, {"class_name": "Int", "config": {"name": "first_units", "default": null, "conditions": [], "min_value": 1, "max_value": 10, "step": 2, "sampling": null}}, {"class_name": "Int", "config": {"name": "num_layers", "default": null, "conditions": [], "min_value": 1, "max_value": 6, "step": 1, "sampling": null}}, {"class_name": "Int", "config": {"name": "units_0", "default": null, "conditions": [], "min_value": 1, "max_value": 10, "step": 2, "sampling": null}}], "values": {"activation": "relu", "first_units": 1, "num_layers": 1, "units_0": 1}}, "seed": 3398, "seed_state": 3402, "tried_so_far": ["abc4593be14e0883abe4a87a90aaee5d"], "hyperband_iterations": 2, "max_epochs": 20, "min_epochs": 1, "factor": 3, "brackets": [{"bracket_num": 2, "rounds": [[{"past_id": null, "id": "237cd0baa5bb1485ff560e1d5aa7ab33"}], [], []]}], "current_bracket": 2, "current_iteration": 0}